wandb_tools/__init__.py
wandb_tools/copy_view.py
wandb_tools/lightning.py
wandb_tools/table.py
wandb_tools-0.1.2.dist-info/METADATA
wandb_tools-0.1.2.dist-info/WHEEL
wandb_tools-0.1.2.dist-info/RECORD
