Metadata-Version: 2.4
Name: wandb-tools
Version: 0.1.2
Summary: Add your description here
Author-email: richarddwang <richardyy1188@gmail.com>
Requires-Python: >=3.12
Requires-Dist: loguru>=0.7.3
Requires-Dist: pandas>=2.3.2
Requires-Dist: python-dotenv>=1.1.1
Requires-Dist: wandb-workspaces>=0.1.18
Requires-Dist: wandb>=0.22.0
